.travis.yml
README.rst
bootstrap.py
buildout.cfg
pre-commit-check.sh
setup.py
validation-files.yaml
validation-options.yaml
docs/HISTORY.rst
docs/LICENSE.rst
docs/api.rst
docs/conf.py
docs/conventions.rst
docs/env.rst
docs/index.rst
docs/release.rst
src/wordai/__init__.py
src/wordai/exceptions.py
src/wordai/regular.py
src/wordai/turing.py
src/wordai.egg-info/PKG-INFO
src/wordai.egg-info/SOURCES.txt
src/wordai.egg-info/dependency_links.txt
src/wordai.egg-info/not-zip-safe
src/wordai.egg-info/requires.txt
src/wordai.egg-info/top_level.txt
src/wordai/tests/__init__.py
src/wordai/tests/test_wordai.py